chess_analyst/__init__.py
chess_analyst/analyzer.py
chess_analyst/classifier.py
chess_analyst/cli.py
chess_analyst/engine.py
chess_analyst/pgn_parser.py
chess_post_analyst-1.0.1.dist-info/licenses/LICENSE
tests/__init__.py
tests/test_classifier.py
tests/test_pgn_parser.py
tests/test_web_app.py
chess_post_analyst-1.0.1.dist-info/METADATA
chess_post_analyst-1.0.1.dist-info/WHEEL
chess_post_analyst-1.0.1.dist-info/entry_points.txt
chess_post_analyst-1.0.1.dist-info/top_level.txt
chess_post_analyst-1.0.1.dist-info/RECORD
