Metadata-Version: 2.4
Name: chess-post-analyst
Version: 1.0.1
Summary: A professional chess post-game analysis tool with CLI and web interfaces
Home-page: https://github.com/lekhanpro/chess-post-game-analyst
Author: Lekhan
Author-email: 
Project-URL: Bug Reports, https://github.com/lekhanpro/chess-post-game-analyst/issues
Project-URL: Source, https://github.com/lekhanpro/chess-post-game-analyst
Keywords: chess analysis stockfish pgn game-analysis chess-engine
Classifier: Development Status :: 5 - Production/Stable
Classifier: Intended Audience :: Developers
Classifier: Intended Audience :: End Users/Desktop
Classifier: Topic :: Games/Entertainment :: Board Games
Classifier: License :: OSI Approved :: MIT License
Classifier: Programming Language :: Python :: 3
Classifier: Programming Language :: Python :: 3.8
Classifier: Programming Language :: Python :: 3.9
Classifier: Programming Language :: Python :: 3.10
Classifier: Programming Language :: Python :: 3.11
Classifier: Programming Language :: Python :: 3.12
Classifier: Operating System :: OS Independent
Requires-Python: >=3.8
License-File: LICENSE
Requires-Dist: python-chess>=1.999
Requires-Dist: stockfish>=3.28.0
Requires-Dist: click>=8.1.7
Requires-Dist: colorama>=0.4.6
Requires-Dist: tqdm>=4.66.1
Requires-Dist: flask>=3.0.0
Requires-Dist: flask-cors>=4.0.0
Requires-Dist: python-dotenv>=1.0.0
Requires-Dist: markdown>=3.5.1
Dynamic: author
Dynamic: classifier
Dynamic: description
Dynamic: description-content-type
Dynamic: home-page
Dynamic: keywords
Dynamic: license-file
Dynamic: project-url
Dynamic: requires-dist
Dynamic: requires-python
Dynamic: summary
